cyspacedork/__init__.py
cyspacedork/spacedork.py
cyspacedork/reps/__init__.py
cyspacedork/reps/zoomeye.py
spacedork/__init__.py
spacedork/spacedork.py
spacedork/reps/__init__.py
spacedork/reps/zoomeye.py
cyspacedork-3.1.2.dist-info/METADATA
cyspacedork-3.1.2.dist-info/WHEEL
cyspacedork-3.1.2.dist-info/entry_points.txt
cyspacedork-3.1.2.dist-info/top_level.txt
cyspacedork-3.1.2.dist-info/RECORD
