Metadata-Version: 2.1
Name: cyspacedork
Version: 3.1.2
Home-page: 
Author: 
Author-email: tongchengbin@outlook.com
Maintainer: 
Keywords: dork search
Platform: any
Requires-Python: >=3.6
Requires-Dist: httpx
Requires-Dist: PyYAML
